pelikan/Pelikan.py
pelikan/__init__.py
tests/__init__.py
tests/test.py
pelikan-0.0.5.dist-info/LICENSE
pelikan-0.0.5.dist-info/METADATA
pelikan-0.0.5.dist-info/WHEEL
pelikan-0.0.5.dist-info/entry_points.txt
pelikan-0.0.5.dist-info/top_level.txt
pelikan-0.0.5.dist-info/RECORD
