Metadata-Version: 2.1
Name: pelikan
Version: 0.0.5
Summary: a jupyter notebook tool to make notebooks comment-free
Home-page: https://github.com/ozlerhakan/palikan
Author: Hakan Ozler
Author-email: ozler.hakan@gmail.com
License: UNKNOWN
Project-URL: Bug Tracker, https://github.com/ozlerhakan/pelikan/issues
Keywords: python,jupyter,notebooks
Platform: UNKNOWN
Classifier: Programming Language :: Python :: 3
Classifier: License :: OSI Approved :: MIT License
Classifier: Operating System :: OS Independent
Requires-Python: >=3.7
License-File: LICENSE
Requires-Dist: nbconvert (>=6.2.0)
Requires-Dist: nbformat (>=5.1.3)
